kir/__init__.py
kir-1.0.1.dist-info/LICENSE.txt
kir-1.0.1.dist-info/METADATA
kir-1.0.1.dist-info/RECORD
kir-1.0.1.dist-info/WHEEL
kir-1.0.1.dist-info/top_level.txt
src/__init__.py
