Metadata-Version: 2.1
Name: kir
Version: 1.0.1
Summary: Kir tu kosse khare Taki
Home-page: https://github.com/jhnnysins/kir.git
Author: Johnny Sins
Author-email: jhnnysins@gmail.com
License: MIT
Platform: UNKNOWN
